HashToDocx/Library.py
HashToDocx/__init__.py
HashToDocx-1.0.1.dist-info/LICENSE
HashToDocx-1.0.1.dist-info/METADATA
HashToDocx-1.0.1.dist-info/WHEEL
HashToDocx-1.0.1.dist-info/top_level.txt
HashToDocx-1.0.1.dist-info/RECORD
