Metadata-Version: 2.1
Name: HashToDocx
Version: 1.0.1
Summary: Write File Information to docx(for Forensic)
Home-page: https://github.com/qerogram/HashToDocx
Author: Qerogram
Author-email: qerogram@google.com
Classifier: Programming Language :: Python :: 3
Classifier: License :: OSI Approved :: MIT License
Requires-Python: >=3.7
License-File: LICENSE
